journalplots/__init__.py
journalplots/style.py
journalplots-0.1.21.dist-info/METADATA
journalplots-0.1.21.dist-info/WHEEL
journalplots-0.1.21.dist-info/RECORD
