Metadata-Version: 2.4
Name: journalplots
Version: 0.1.21
Summary: A package for consistent journal-ready matplotlib plotting styles
Author-email: Baljyot Singh Parmar <baljyotparmar@hotmail.com>
License: MIT
Classifier: License :: OSI Approved :: MIT License
Classifier: Operating System :: OS Independent
Classifier: Programming Language :: Python :: 3
Requires-Python: >=3.8
Requires-Dist: cycler>=0.12.1
Requires-Dist: matplotlib>=3.0.0
